bourguibagpt/__init__.py
bourguibagpt/config.py
bourguibagpt/main.py
bourguibagpt/validators.py
bourguibagpt/windows.py
bourguibagpt-2.0.1.dist-info/METADATA
bourguibagpt-2.0.1.dist-info/WHEEL
bourguibagpt-2.0.1.dist-info/entry_points.txt
bourguibagpt-2.0.1.dist-info/top_level.txt
bourguibagpt-2.0.1.dist-info/RECORD
