Metadata-Version: 2.2
Name: bourguibagpt
Version: 2.0.1
Summary: Tunisian Shell Command Assistant
Home-page: https://github.com/AzizBahloul/PromptToCommand
Author: Si Aziz Bahloul
Author-email: azizbahloul3@gmail.com
License: MIT
Classifier: Programming Language :: Python :: 3
Classifier: License :: OSI Approved :: MIT License
Classifier: Operating System :: OS Independent
Classifier: Development Status :: 4 - Beta
Classifier: Intended Audience :: Developers
Classifier: Natural Language :: English
Classifier: Topic :: Software Development :: Libraries :: Python Modules
Requires-Python: >=3.6
Requires-Dist: rich>=13.6.0
Requires-Dist: requests>=2.25.0
Requires-Dist: psutil>=5.9.0
Requires-Dist: inquirer>=3.1.0
Requires-Dist: tqdm>=4.65.0
